pyatlonajuno/__init__.py
pyatlonajuno/cli.py
pyatlonajuno/lib.py
pyatlonajuno-1.1.1.dist-info/AUTHORS.rst
pyatlonajuno-1.1.1.dist-info/LICENSE
pyatlonajuno-1.1.1.dist-info/METADATA
pyatlonajuno-1.1.1.dist-info/WHEEL
pyatlonajuno-1.1.1.dist-info/entry_points.txt
pyatlonajuno-1.1.1.dist-info/top_level.txt
pyatlonajuno-1.1.1.dist-info/RECORD
