Metadata-Version: 2.1
Name: pyatlonajuno
Version: 1.1.1
Summary: Python Library for controlling the Atlona Juno 451 HDMI Switch
Home-page: https://github.com/hughsaunders/pyatlonajuno
Author: Hugh Saunders
Author-email: hugh@wherenow.org
License: MIT license
Keywords: pyatlonajuno
Platform: UNKNOWN
Classifier: Development Status :: 2 - Pre-Alpha
Classifier: Intended Audience :: Developers
Classifier: License :: OSI Approved :: MIT License
Classifier: Natural Language :: English
Classifier: Programming Language :: Python :: 3
Classifier: Programming Language :: Python :: 3.4
Classifier: Programming Language :: Python :: 3.5
Classifier: Programming Language :: Python :: 3.6
Classifier: Programming Language :: Python :: 3.7
Requires-Dist: Click (>=7.0)
Requires-Dist: requests
